PatchQuant/__init__.py
PatchQuant/patch_quant.py
PatchQuant/AbstractClasses/__init__.py
PatchQuant/AbstractClasses/data_handler.py
PatchQuant/AbstractClasses/event_loop.py
PatchQuant/AbstractClasses/portfolio.py
PatchQuant/AbstractClasses/trader.py
PatchQuant/DataHandlers/__init__.py
PatchQuant/DataHandlers/alpaca.py
PatchQuant/EventLoops/__init__.py
PatchQuant/EventLoops/backtesting_loop.py
PatchQuant/Events/Stock.py
PatchQuant/Events/__init__.py
PatchQuant/Portfolios/__init__.py
PatchQuant/Portfolios/my_portfolio.py
PatchQuant/Resources/__init__.py
PatchQuant/Resources/nyse_holidays.py
patch_quant/__init__.py
patch_quant/patch_quant.py
patch_quant/AbstractClasses/__init__.py
patch_quant/AbstractClasses/data_handler.py
patch_quant/AbstractClasses/event_loop.py
patch_quant/AbstractClasses/portfolio.py
patch_quant/AbstractClasses/trader.py
patch_quant/DataHandlers/__init__.py
patch_quant/DataHandlers/alpaca.py
patch_quant/EventLoops/__init__.py
patch_quant/EventLoops/backtesting_loop.py
patch_quant/Events/Stock.py
patch_quant/Events/__init__.py
patch_quant/Portfolios/__init__.py
patch_quant/Portfolios/my_portfolio.py
patch_quant/Resources/__init__.py
patch_quant/Resources/nyse_holidays.py
PatchQuant-0.1.4.dist-info/LICENSE.md
PatchQuant-0.1.4.dist-info/METADATA
PatchQuant-0.1.4.dist-info/WHEEL
PatchQuant-0.1.4.dist-info/entry_points.txt
PatchQuant-0.1.4.dist-info/top_level.txt
PatchQuant-0.1.4.dist-info/RECORD
