Metadata-Version: 2.1
Name: PatchQuant
Version: 0.1.4
Summary: Backtesting platform built around Alpaca Exchange
Home-page: https://github.com/Patch-Traders/BackTester
Author: Hal and Carson
Author-email: owens155@purdue.edu
License: UNKNOWN
Keywords: backtesting,trading,quantitative finance,finance
Platform: UNKNOWN
Classifier: Programming Language :: Python :: 3.7
Classifier: License :: OSI Approved :: MIT License
Requires-Python: >=3.6
